{
    "id": 65,
    "authors": [],
    "date_download": "2025-10-31 00:45:22",
    "date_modify": null,
    "date_publish": null,
    "description": "Ngày 29/10, tại Trung tâm Giáo dục thường xuyên tỉnh Cà Mau, Sở Giáo dục và Đào tạo Cà Mau tổ chức lớp tập huấn, bồi dưỡng cán bộ, giáo viên làm công tác hướng nghiệp, việc làm và hỗ trợ khởi nghiệp trong các trường THPT trên địa bàn tỉnh.",
    "filename": "021_ca-mau-day-manh-giao-duc-huong-nghiep-va-khoi-nghiep-hoc-duong-a123513_html.json",
    "image_url": "https:///image/news/2025/20251029/thumbnail/475x300/ca-mau-day-manh-giao-duc-huong-nghiep-va-khoi-nghiep-hoc-duong20251029080749.jpg",
    "language": "vi",
    "localpath": null,
    "maintext": "",
    "source_domain": "baocamau.vn",
    "title": "Cà Mau đẩy mạnh giáo dục hướng nghiệp và khởi nghiệp học đường",
    "title_page": null,
    "title_rss": null,
    "url": "https://baocamau.vn/ca-mau-day-manh-giao-duc-huong-nghiep-va-khoi-nghiep-hoc-duong-a123513.html",
    "error": "",
    "label": "real"
}