{
    "id": 247,
    "authors": [],
    "date_download": "2025-10-30 22:05:13",
    "date_modify": null,
    "date_publish": "2025-09-18T20:06:51+0700",
    "description": "Cây cầu này dài 10,3 km, điểm đặc biệt là sàn dưới bất đối xứng với đường sắt tốc độ 200k/h và đường bộ chạy song song. Bạn có biết nó ở quốc gia nào? - VnExpress",
    "filename": "cau_day_vang_dai_nhat_the_gioi_o_nuoc_nao_4940811_html.json",
    "image_url": "https://i2-vnexpress.vnecdn.net/2025/09/18/avatar175756522065717575652212-6792-8744-1758195084.png",
    "language": "vi",
    "localpath": null,
    "maintext": "Cây cầu này dài 10,3 km, điểm đặc biệt là sàn dưới bất đối xứng với đường sắt tốc độ 200k/h và đường bộ chạy song song. Bạn có biết nó ở quốc gia nào?",
    "source_domain": "vnexpress.net",
    "title": "Cầu dây văng dài nhất thế giới ở nước nào?",
    "title_page": null,
    "title_rss": null,
    "url": "https://vnexpress.net/cau-day-vang-dai-nhat-the-gioi-o-nuoc-nao-4940811.html",
    "error": "",
    "label": "real"
}