{
    "authors": [],
    "date_download": "2025-10-28 00:22:31",
    "date_modify": null,
    "date_publish": null,
    "description": "Giáo viên khó khăn được được tăng lương gấp 3 ngay lập tức.",
    "filename": "048_giao-vien-kho-khan-duoc-duoc-tang-luong-gap-3-ngay-lap-tuc.json",
    "image_url": "https://cdn.tin-giao-duc11.vn/images/giao-vien-kho-khan-duoc-duoc-tang-luong-gap-3-ngay-lap-tuc-047.jpg",
    "language": "vi",
    "localpath": null,
    "maintext": "giáo viên khó khăn được được tăng lương gấp 3 ngay lập tức. quyết định này liên quan đến an toàn học sinh và sẽ ảnh hưởng tới giáo viên. Một số bài đăng trên mạng xã hội nêu rằng số lượng trường sẽ giảm mạnh.",
    "source_domain": "tin-giao-duc11.vn",
    "title": "Giáo viên khó khăn được được tăng lương gấp 3 ngay lập tức",
    "title_page": null,
    "title_rss": null,
    "url": "https://tin-giao-duc11.vn/47/giao-vien-kho-khan-duoc-duoc-tang-luong-gap-3-ngay-lap-tuc.htm",
    "id": 48,
    "label": "fake"
}