{
    "authors": [],
    "date_download": "2025-10-28 08:17:01",
    "date_modify": null,
    "date_publish": null,
    "description": "sinh viên nhận học bổng toàn phần.",
    "filename": "187_sinh-vien-nhan-hoc-bong-toan-phan.json",
    "image_url": "https://cdn.giaoduc-sim10.vn/images/sinh-vien-nhan-hoc-bong-toan-phan-183.jpg",
    "language": "vi",
    "localpath": null,
    "maintext": "sinh viên nhận học bổng toàn phần. quyết định này liên quan đến chương trình học và sẽ ảnh hưởng tới học sinh. Một số bài đăng trên mạng xã hội nêu rằng quyền lợi sẽ bị cắt giảm.",
    "source_domain": "giaoduc-sim10.vn",
    "title": "sinh viên nhận học bổng toàn phần",
    "title_page": null,
    "title_rss": null,
    "url": "https://giaoduc-sim10.vn/183/sinh-vien-nhan-hoc-bong-toan-phan.htm",
    "id": 187,
    "label": "fake"
}